{
    "nodes": [
        {
            "id": "5",
            "type": "default",
            "targetPosition": "top",
            "position": {
                "x": 0,
                "y": 0
            },
            "data": {
                "type": "call",
                "text": "np.random.RandomState",
                "identifier": "RandomState",
                "output_variable": "rng",
                "label": "np.random.RandomState"
            }
        },
        {
            "id": "8",
            "type": "default",
            "targetPosition": "top",
            "position": {
                "x": 0,
                "y": 0
            },
            "data": {
                "type": "attribute",
                "text": "np.random",
                "identifier": [
                    "np",
                    "random"
                ],
                "label": "np.random"
            }
        },
        {
            "id": "12",
            "type": "default",
            "targetPosition": "top",
            "position": {
                "x": 0,
                "y": 0
            },
            "data": {
                "type": "integer",
                "text": "1",
                "label": "1"
            }
        }
    ],
    "edges": [
        {
            "id": "edge-1",
            "source": "8",
            "target": "5",
            "type": "smoothstep"
        },
        {
            "id": "edge-2",
            "source": "12",
            "target": "5",
            "type": "smoothstep"
        }
    ]
}